{
	"info": {
		"_postman_id": "70dbdc07-a96f-4212-acb8-39d92daae569",
		"name": "EventMgmtApis",
		"schema": "https://schema.getpostman.com/json/collection/v2.1.0/collection.json",
		"_exporter_id": "29157843"
	},
	"item": [
		{
			"name": "Auth Apis",
			"item": [
				{
					"name": "login",
					"request": {
						"method": "POST",
						"header": [
							{
								"key": "Accept",
								"value": "application/json",
								"type": "text"
							}
						],
						"body": {
							"mode": "raw",
							"raw": "{\r\n    \"email\":\"admin2@gmail.com\",\r\n    \"password\":\"123\"\r\n}",
							"options": {
								"raw": {
									"language": "json"
								}
							}
						},
						"url": {
							"raw": "http://localhost:8000/api/login/",
							"protocol": "http",
							"host": [
								"localhost"
							],
							"port": "8000",
							"path": [
								"api",
								"login",
								""
							]
						}
					},
					"response": []
				},
				{
					"name": "RigsterForTesting",
					"request": {
						"method": "POST",
						"header": [
							{
								"key": "Accept",
								"value": "application/json",
								"type": "text"
							}
						],
						"body": {
							"mode": "raw",
							"raw": "{\r\n     \"name\":\"admin2\",\r\n     \"email\":\"admin2@gmail.com\",\r\n     \"password\":\"123\",\r\n     \"role\":\"admin\"\r\n}",
							"options": {
								"raw": {
									"language": "json"
								}
							}
						},
						"url": {
							"raw": "http://localhost:8000/api/register/",
							"protocol": "http",
							"host": [
								"localhost"
							],
							"port": "8000",
							"path": [
								"api",
								"register",
								""
							]
						}
					},
					"response": []
				},
				{
					"name": "logout",
					"request": {
						"auth": {
							"type": "bearer",
							"bearer": [
								{
									"key": "token",
									"value": "13|dev0W2gmRn1fIC46ARXT0vHRxLGFbSdZOWhzIjDnmWec3b5376b",
									"type": "string"
								}
							]
						},
						"method": "POST",
						"header": [
							{
								"key": "Accept",
								"value": "application/json",
								"type": "text"
							}
						],
						"url": {
							"raw": "http://{{ip}}:8000/api/logout/",
							"protocol": "http",
							"host": [
								"{{ip}}"
							],
							"port": "8000",
							"path": [
								"api",
								"logout",
								""
							]
						}
					},
					"response": []
				}
			],
			"description": "/login\n\n/register\n\n\\-Register is only for demo. So tester can add users in database"
		},
		{
			"name": "Event Apis",
			"item": [
				{
					"name": "GetAllEvents",
					"request": {
						"auth": {
							"type": "bearer",
							"bearer": [
								{
									"key": "token",
									"value": "5|devWpPUdVQ4vnG7nJbcyW5eahf1DeEd1MIRrWeuDAxn9aac60e4",
									"type": "string"
								}
							]
						},
						"method": "GET",
						"header": [
							{
								"key": "Accept",
								"value": "application/json",
								"type": "text"
							}
						],
						"url": {
							"raw": "http://localhost:8000/api/events/3",
							"protocol": "http",
							"host": [
								"localhost"
							],
							"port": "8000",
							"path": [
								"api",
								"events",
								"3"
							]
						}
					},
					"response": []
				},
				{
					"name": "Getevent by id",
					"request": {
						"auth": {
							"type": "bearer",
							"bearer": [
								{
									"key": "token",
									"value": "5|devWpPUdVQ4vnG7nJbcyW5eahf1DeEd1MIRrWeuDAxn9aac60e4",
									"type": "string"
								}
							]
						},
						"method": "GET",
						"header": [
							{
								"key": "Accept",
								"value": "application/json",
								"type": "text"
							}
						],
						"url": {
							"raw": "http://localhost:8000/api/events/3",
							"protocol": "http",
							"host": [
								"localhost"
							],
							"port": "8000",
							"path": [
								"api",
								"events",
								"3"
							]
						}
					},
					"response": []
				},
				{
					"name": "addevent",
					"request": {
						"auth": {
							"type": "bearer",
							"bearer": [
								{
									"key": "token",
									"value": "6|dev7kvE6ao5SPsV5gLpnnrskeXK6tzv1N43WRfacz0wacaa86bd",
									"type": "string"
								}
							]
						},
						"method": "POST",
						"header": [
							{
								"key": "Accept",
								"value": "application/json",
								"type": "text"
							}
						],
						"body": {
							"mode": "raw",
							"raw": "{\r\n    \"EventTitle\":\"newop\",\r\n    \"EventDesc\":\"Many people is facing water problem in there home\",\r\n    \"EventDate\":\"2025-09-01 14:30:00\"\r\n}",
							"options": {
								"raw": {
									"language": "json"
								}
							}
						},
						"url": {
							"raw": "http://{{ip}}:8000/api/events/",
							"protocol": "http",
							"host": [
								"{{ip}}"
							],
							"port": "8000",
							"path": [
								"api",
								"events",
								""
							]
						}
					},
					"response": []
				},
				{
					"name": "update Event",
					"request": {
						"auth": {
							"type": "bearer",
							"bearer": [
								{
									"key": "token",
									"value": "6|dev7kvE6ao5SPsV5gLpnnrskeXK6tzv1N43WRfacz0wacaa86bd",
									"type": "string"
								}
							]
						},
						"method": "PUT",
						"header": [
							{
								"key": "Accept",
								"value": "application/json",
								"type": "text"
							}
						],
						"body": {
							"mode": "raw",
							"raw": "    {\r\n        \"EventTitle\": \"updatedop\",\r\n        \"EventDesc\": \"Many people is facing water problem in there home\",\r\n        \"EventDate\": \"2025-09-01 14:30:00\"\r\n    }",
							"options": {
								"raw": {
									"language": "json"
								}
							}
						},
						"url": {
							"raw": "http://localhost:8000/api/events/4",
							"protocol": "http",
							"host": [
								"localhost"
							],
							"port": "8000",
							"path": [
								"api",
								"events",
								"4"
							]
						}
					},
					"response": []
				},
				{
					"name": "delete event",
					"request": {
						"auth": {
							"type": "bearer",
							"bearer": [
								{
									"key": "token",
									"value": "6|dev7kvE6ao5SPsV5gLpnnrskeXK6tzv1N43WRfacz0wacaa86bd",
									"type": "string"
								}
							]
						},
						"method": "DELETE",
						"header": [
							{
								"key": "Accept",
								"value": "application/json",
								"type": "text"
							}
						],
						"url": {
							"raw": "http://{{ip}}:8000/api/events/3",
							"protocol": "http",
							"host": [
								"{{ip}}"
							],
							"port": "8000",
							"path": [
								"api",
								"events",
								"3"
							]
						}
					},
					"response": []
				}
			]
		}
	],
	"event": [
		{
			"listen": "prerequest",
			"script": {
				"type": "text/javascript",
				"packages": {},
				"exec": [
					""
				]
			}
		},
		{
			"listen": "test",
			"script": {
				"type": "text/javascript",
				"packages": {},
				"exec": [
					""
				]
			}
		}
	],
	"variable": [
		{
			"key": "ip",
			"value": "localhost"
		}
	]
}